[
    {
        "Aktiv": "Nein von: 2011-2015",
        "ArtistID": 3651,
        "Augenfarbe": "",
        "BabePedia": "",
        "Birth_Place": "Wilson, NC, USA\u00a0",
        "Bodytyp": "",
        "Boobs": "34C",
        "Geburtstag": "05.11.1992",
        "Geschlecht": 1,
        "Gewicht": 45,
        "Groesse": 157,
        "Haarfarbe": "Blond",
        "IAFDLink": "https://www.iafd.com/person.rme/perfid=madisonchandler/gender=f/madison-chandler.htm",
        "Name": "Madison Chandler",
        "Nation": "US Amerikaner",
        "OnlyFans": "",
        "Ordner": "Madison Chandler",
        "Piercing": "Lower right lip; Navel; Both nipples; Below left eye/upper left cheek",
        "Rassen": "Kaukasien",
        "Tattoo": "4 Butterflies on left shoulder blade; Several small stars lower right back; Script \"Sweetpea\" and 2 paw marks right ribs"
    }
]